setup.py
butler/__init__.py
butler/client.py
butler/client_rpc_proxy.py
butler/router.py
butler/service.py
butler/sink.py
butler.egg-info/PKG-INFO
butler.egg-info/SOURCES.txt
butler.egg-info/dependency_links.txt
butler.egg-info/requires.txt
butler.egg-info/top_level.txt